spot/__init__.py
spot/_buddy.cpython-310-x86_64-linux-gnu.a
spot/_buddy.cpython-310-x86_64-linux-gnu.so
spot/_buddy.cpython-311-x86_64-linux-gnu.a
spot/_buddy.cpython-311-x86_64-linux-gnu.so
spot/_buddy.cpython-312-x86_64-linux-gnu.a
spot/_buddy.cpython-312-x86_64-linux-gnu.so
spot/_buddy.cpython-313-x86_64-linux-gnu.a
spot/_buddy.cpython-313-x86_64-linux-gnu.so
spot/_gen.cpython-310-x86_64-linux-gnu.a
spot/_gen.cpython-310-x86_64-linux-gnu.so
spot/_gen.cpython-311-x86_64-linux-gnu.a
spot/_gen.cpython-311-x86_64-linux-gnu.so
spot/_gen.cpython-312-x86_64-linux-gnu.a
spot/_gen.cpython-312-x86_64-linux-gnu.so
spot/_gen.cpython-313-x86_64-linux-gnu.a
spot/_gen.cpython-313-x86_64-linux-gnu.so
spot/_impl.cpython-310-x86_64-linux-gnu.a
spot/_impl.cpython-310-x86_64-linux-gnu.so
spot/_impl.cpython-311-x86_64-linux-gnu.a
spot/_impl.cpython-311-x86_64-linux-gnu.so
spot/_impl.cpython-312-x86_64-linux-gnu.a
spot/_impl.cpython-312-x86_64-linux-gnu.so
spot/_impl.cpython-313-x86_64-linux-gnu.a
spot/_impl.cpython-313-x86_64-linux-gnu.so
spot/_ltsmin.cpython-310-x86_64-linux-gnu.a
spot/_ltsmin.cpython-310-x86_64-linux-gnu.so
spot/_ltsmin.cpython-311-x86_64-linux-gnu.a
spot/_ltsmin.cpython-311-x86_64-linux-gnu.so
spot/_ltsmin.cpython-312-x86_64-linux-gnu.a
spot/_ltsmin.cpython-312-x86_64-linux-gnu.so
spot/_ltsmin.cpython-313-x86_64-linux-gnu.a
spot/_ltsmin.cpython-313-x86_64-linux-gnu.so
spot/aux_.py
spot/buddy.py
spot/gen.py
spot/impl.py
spot/jupyter.py
spot/libbddx.a
spot/libbddx.so.0.0.0
spot/libspot.a
spot/libspot.so.0.0.0
spot/libspotgen.a
spot/libspotgen.so.0.0.0
spot/libspotltsmin.a
spot/libspotltsmin.so.0.0.0
spot/ltsmin.py
spottl.libs/libbddx-b13be169.so.0.0.0
spottl.libs/libspot-22277c4f.so.0.0.0
spottl.libs/libspotgen-ba43728d.so.0.0.0
spottl.libs/libspotltsmin-db4d1333.so.0.0.0
spottl-2.13.0.1.dist-info/LICENSE
spottl-2.13.0.1.dist-info/METADATA
spottl-2.13.0.1.dist-info/WHEEL
spottl-2.13.0.1.dist-info/RECORD
