Metadata-Version: 2.3
Name: spottl
Version: 2.13.0.1
Summary: "Pip-installable version of spot library"
License: GNP
Author: Mikihisa Yuasa
Author-email: mik0915yua@outlook.com
Requires-Python: >=3.10,<3.14
Classifier: License :: Other/Proprietary License
Classifier: Programming Language :: Python :: 3
Classifier: Programming Language :: Python :: 3.10
Classifier: Programming Language :: Python :: 3.11
Classifier: Programming Language :: Python :: 3.12
Classifier: Programming Language :: Python :: 3.13
